ayaka_games/.git/COMMIT_EDITMSG
ayaka_games/.git/config
ayaka_games/.git/description
ayaka_games/.git/FETCH_HEAD
ayaka_games/.git/HEAD
ayaka_games/.git/hooks/applypatch-msg.sample
ayaka_games/.git/hooks/commit-msg.sample
ayaka_games/.git/hooks/fsmonitor-watchman.sample
ayaka_games/.git/hooks/post-update.sample
ayaka_games/.git/hooks/pre-applypatch.sample
ayaka_games/.git/hooks/pre-commit.sample
ayaka_games/.git/hooks/pre-merge-commit.sample
ayaka_games/.git/hooks/pre-push.sample
ayaka_games/.git/hooks/pre-rebase.sample
ayaka_games/.git/hooks/pre-receive.sample
ayaka_games/.git/hooks/prepare-commit-msg.sample
ayaka_games/.git/hooks/push-to-checkout.sample
ayaka_games/.git/hooks/update.sample
ayaka_games/.git/index
ayaka_games/.git/info/exclude
ayaka_games/.git/logs/HEAD
ayaka_games/.git/logs/refs/heads/master
ayaka_games/.git/logs/refs/remotes/origin/master
ayaka_games/.git/objects/00/209596e2185f4dca1b6ee14e42d031e95bcc9c
ayaka_games/.git/objects/00/93d0f5406a874f9940a8b24b4dced9279e28f0
ayaka_games/.git/objects/00/c8db389730d682c305d3849a94217ccb37edfb
ayaka_games/.git/objects/00/cf5773e9d412d708e2abd8a84479cb04632559
ayaka_games/.git/objects/00/e3937d2efc50f2579b7c10cadc09a21b1b62ef
ayaka_games/.git/objects/00/f4ec19f72bae0867a8ba1d483483752effb552
ayaka_games/.git/objects/02/0f23bb9085928349402e33ca186327ae7f98b2
ayaka_games/.git/objects/02/1ed897c6dcad18323a8ce45650303fed779603
ayaka_games/.git/objects/02/2524fbfcb2e31b55ae58f6603da7e84c029cd9
ayaka_games/.git/objects/02/2f142935a6645cda50044317efc2b45ba43381
ayaka_games/.git/objects/02/37d6df730e8ae90bfd6a79e8817acaed76fa14
ayaka_games/.git/objects/02/fd43319f290e73add6529f5b103290b66d45d5
ayaka_games/.git/objects/03/14a10372d3a0162b19c3be2fd1bee92b6ba898
ayaka_games/.git/objects/03/6650b66280db2c32eac324feaefc6a12c97a15
ayaka_games/.git/objects/03/a8c245b8cc154f7882b77096c56d2815e76352
ayaka_games/.git/objects/03/e72ea1785bbdbed6c1f0725bc1f5fc1fce4327
nonebot_plugin_ayaka_games-0.5.7.dist-info/LICENSE
nonebot_plugin_ayaka_games-0.5.7.dist-info/METADATA
nonebot_plugin_ayaka_games-0.5.7.dist-info/WHEEL
nonebot_plugin_ayaka_games-0.5.7.dist-info/RECORD
