Metadata-Version: 2.1
Name: nonebot-plugin-ayaka-games
Version: 0.5.7
Summary: ayaka小游戏合集
Home-page: https://github.com/bridgeL/nonebot-plugin-ayaka-games
License: MIT
Author: Su
Author-email: wxlxy316@163.com
Requires-Python: >=3.10,<4.0
Classifier: License :: OSI Approved :: MIT License
Classifier: Programming Language :: Python :: 3
Classifier: Programming Language :: Python :: 3.10
Classifier: Programming Language :: Python :: 3.11
Requires-Dist: nonebot-plugin-ayaka (>=1.0.2,<1.1.0)
Requires-Dist: pypinyin (>=0.47.1,<0.48.0)
Project-URL: Repository, https://github.com/bridgeL/nonebot-plugin-ayaka-games
